hangman/__init__.py
hangman_lk96er-1.2.dist-info/LICENSE
hangman_lk96er-1.2.dist-info/METADATA
hangman_lk96er-1.2.dist-info/WHEEL
hangman_lk96er-1.2.dist-info/top_level.txt
hangman_lk96er-1.2.dist-info/RECORD
