Metadata-Version: 2.1
Name: hangman-lk96er
Version: 1.2
Summary: A simple hangman game I created. Language: German
Home-page: UNKNOWN
Author: Lucas
Author-email: not_areale@mail.com
License: UNKNOWN
Platform: UNKNOWN
Classifier: Programming Language :: Python :: 3
Classifier: License :: OSI Approved :: MIT License
Classifier: Operating System :: OS Independent
Requires-Python: >=3.6
